GPLWordNet/__init__.py
GPLWordNet/example.py
tests/test1.py
GPLWordNet-1.0.3.dist-info/LICENSE
GPLWordNet-1.0.3.dist-info/METADATA
GPLWordNet-1.0.3.dist-info/WHEEL
GPLWordNet-1.0.3.dist-info/top_level.txt
GPLWordNet-1.0.3.dist-info/RECORD
