Metadata-Version: 2.1
Name: GPLWordNet
Version: 1.0.3
Summary: A tool for generating polarity lexicons with WordNet  package
Author-email: Xuanlong QIN <xuanlongqin.cu@gmail.com>
License: MIT License
Classifier: Programming Language :: Python :: 3
Classifier: License :: OSI Approved :: MIT License
Classifier: Operating System :: OS Independent
Requires-Python: >=3.8
License-File: LICENSE
Requires-Dist: click >=8.1.7
Requires-Dist: joblib >=1.4.2
Requires-Dist: nltk >=3.9.1
Requires-Dist: tqdm ==4.66.5
